tinycp/classifier/__init__.py
tinycp/classifier/base.py
tinycp/classifier/class_conditional.py
tinycp/classifier/marginal.py
tinycp/plot/__init__.py
tinycp/plot/plot.py
tinycp/regressor/__init__.py
tinycp/regressor/base.py
tinycp/regressor/cqr.py
tinycp/regressor/icp.py
tinycp-0.1.2.dist-info/licenses/LICENSE
tinycp-0.1.2.dist-info/METADATA
tinycp-0.1.2.dist-info/WHEEL
tinycp-0.1.2.dist-info/top_level.txt
tinycp-0.1.2.dist-info/RECORD
