Metadata-Version: 2.4
Name: tinycp
Version: 0.1.2
Summary: A small toolbox for conformal prediction
Author-email: Lucas Leão <heylucasleao@gmail.com>
License-Expression: MIT
Keywords: machine-learning,conformal-prediction
Classifier: Programming Language :: Python :: 3
Requires-Python: >=3.10
License-File: LICENSE
Requires-Dist: numpy>=1.24.4
Requires-Dist: venn-abers>=1.4.6
Requires-Dist: scikit-learn>=1.3.0
Requires-Dist: twine>=6.2.0
Provides-Extra: plot
Requires-Dist: plotly>=5.22.0; extra == "plot"
Requires-Dist: kaleido<=0.2.1; extra == "plot"
Provides-Extra: notebook
Requires-Dist: nbformat>=5.10.4; extra == "notebook"
Requires-Dist: ipykernel>=6.7.0; extra == "notebook"
Provides-Extra: all
Requires-Dist: plot; extra == "all"
Requires-Dist: notebook; extra == "all"
Dynamic: license-file
